DEAR_DONG/I2C_IP/02_rtl/COMMON/add_algo.sv
module add_algo #(
    parameter SIZE_DATA = 16
)(
    input  logic [SIZE_DATA-1:0] i_operate_a ,
    input  logic [SIZE_DATA-1:0] i_operate_b ,
    output logic [SIZE_DATA-1:0] o_add       
);

// logic [SIZE_DATA-1:0] g, p;
// logic [SIZE_DATA:0]   c;
//
// assign g = i_operate_a & i_operate_b;
// assign p = i_operate_a ^ i_operate_b;
//
// assign c[0] = 1'b0;
//
// genvar i;
// generate
//     for (i = 0; i < SIZE_DATA; i++) begin : cla_gen
//         assign c[i+1] = g[i] | (p[i] & c[i]);
//         assign o_add[i] = p[i] ^ c[i];
//     end
// endgenerate

assign o_add = i_operate_a + i_operate_b;

endmodule

DEAR_DONG/I2C_IP/02_rtl/COMMON/gen_scl.sv
module gen_scl #(
    parameter SIZE_REG  = 16
)(
    input logic                 i_clk   ,
    input logic                 i_rst_n ,
    input logic                 i_SCL_start ,
    input logic                 i_SCL_en    ,
    input logic [SIZE_REG-1:0]  i_TWIBR ,
    output logic                o_SCL   
);

//==================================
// Variable
//==================================
logic [SIZE_REG-1:0] r_count;
logic [SIZE_REG-1:0] w_count_next;
logic [SIZE_REG-1:0] w_count_add;
logic w_count_stick;

//==================================
// Module 
//==================================
add_algo #(
    .SIZE_DATA  (SIZE_REG)
) add_algo_unit (
    .i_operate_a (r_count),
    .i_operate_b ({{(SIZE_REG-1){1'b0}}, 1'b1}),
    .o_add       (w_count_add)
);

//==================================
// Assign signal
//==================================
assign w_count_next = (i_SCL_en) ? w_count_add : r_count;
assign w_count_stick = (r_count == i_TWIBR);
always_ff @(posedge i_clk or negedge i_rst_n) begin
    if(~i_rst_n) begin
        r_count <= '0;
    end else begin
        r_count <= (w_count_stick) ? '0 : w_count_next;
    end 
end 

always_ff @(posedge i_clk or negedge i_rst_n) begin 
    if(~i_rst_n) begin  
        o_SCL <= 1'b1;
    end else begin
        if(i_SCL_start) begin
            o_SCL <= 1'b0;
        end else begin
            if(w_count_stick) begin
                o_SCL <= ~o_SCL;
            end else begin
                o_SCL <= o_SCL;
            end 
        end 
    end 
end 

endmodule

DEAR_DONG/I2C_IP/03_verif/MODULE/COMMON/gen_scl/tb_gen_scl.sv
`timescale 1ns/1ps

module tb_gen_scl;

    //==================================
    // Parameter
    //==================================
    parameter SIZE_REG = 16;

    //==================================
    // Signal
    //==================================
    logic                 clk;
    logic                 rst_n;
    logic                 i_SCL_start;
    logic                 i_SCL_en;
    logic [SIZE_REG-1:0]  i_TWIBR;
    logic                 o_SCL;

    //==================================
    // DUT
    //==================================
    gen_scl #(
        .SIZE_REG (SIZE_REG)
    ) dut (
        .i_clk       (clk),
        .i_rst_n     (rst_n),
        .i_SCL_start (i_SCL_start),
        .i_SCL_en    (i_SCL_en),
        .i_TWIBR     (i_TWIBR),
        .o_SCL       (o_SCL)
    );

    //==================================
    // Clock gen
    //==================================
    initial clk = 0;
    always #5 clk = ~clk;   // 100 MHz clock (10ns period)

    initial begin
        $dumpfile("tb_gen_scl.vcd");
        $dumpvars(0, tb_gen_scl);
    end 

    //==================================
    // Stimulus
    //==================================
    initial begin
        // Init
        rst_n       = 0;
        i_SCL_start = 0;
        i_SCL_en    = 0;
        i_TWIBR     = 16'd4;   // Divide factor

        // Release reset
        #50 rst_n = 1;

        // Enable SCL
        #20 i_SCL_en = 1;

        // Start condition
        #100 i_SCL_start = 1;
        #20  i_SCL_start = 0;

        // Run for some cycles
        #500;

        // Change divider
        i_TWIBR = 16'd2;
        #500;

        // Stop SCL
        i_SCL_en = 0;
        #200;

        $stop;
    end

endmodule

DEAR_DONG/I2C_IP/03_verif/MODULE/COMMON/gen_scl/tb_gen_scl.vcd
$version Generated by VerilatedVcd $end
$timescale 1ps $end
 $scope module TOP $end
  $scope module tb_gen_scl $end
   $var wire 32 - SIZE_REG [31:0] $end
   $var wire 1 & clk $end
   $var wire 1 ' rst_n $end
   $var wire 1 ( i_SCL_start $end
   $var wire 1 ) i_SCL_en $end
   $var wire 16 * i_TWIBR [15:0] $end
   $var wire 1 # o_SCL $end
   $scope module dut $end
    $var wire 32 - SIZE_REG [31:0] $end
    $var wire 1 & i_clk $end
    $var wire 1 ' i_rst_n $end
    $var wire 1 ( i_SCL_start $end
    $var wire 1 ) i_SCL_en $end
    $var wire 16 * i_TWIBR [15:0] $end
    $var wire 1 # o_SCL $end
    $var wire 16 $ r_count [15:0] $end
    $var wire 16 + w_count_next [15:0] $end
    $var wire 16 % w_count_add [15:0] $end
    $var wire 1 , w_count_stick $end
    $scope module add_algo_unit $end
     $var wire 32 - SIZE_DATA [31:0] $end
     $var wire 16 $ i_operate_a [15:0] $end
     $var wire 16 . i_operate_b [15:0] $end
     $var wire 16 % o_add [15:0] $end
    $upscope $end
   $upscope $end
  $upscope $end
 $upscope $end
$enddefinitions $end


#0
0#
b0000000000000000 $
b0000000000000001 %
0&
0'
0(
0)
b0000000000000100 *
b0000000000000000 +
0,
b00000000000000000000000000010000 -
b0000000000000001 .
#5000
1#
1&
#10000
0&
#15000
1&
#20000
0&
#25000
1&
#30000
0&
#35000
1&
#40000
0&
#45000
1&
#50000
0&
1'
#55000
1&
#60000
0&
#65000
1&
#70000
0&
1)
b0000000000000001 +
#75000
b0000000000000001 $
b0000000000000010 %
1&
b0000000000000010 +
#80000
0&
#85000
b0000000000000010 $
b0000000000000011 %
1&
b0000000000000011 +
#90000
0&
#95000
b0000000000000011 $
b0000000000000100 %
1&
b0000000000000100 +
#100000
0&
#105000
b0000000000000100 $
b0000000000000101 %
1&
b0000000000000101 +
1,
#110000
0&
#115000
0#
b0000000000000000 $
b0000000000000001 %
1&
b0000000000000001 +
0,
#120000
0&
#125000
b0000000000000001 $
b0000000000000010 %
1&
b0000000000000010 +
#130000
0&
#135000
b0000000000000010 $
b0000000000000011 %
1&
b0000000000000011 +
#140000
0&
#145000
b0000000000000011 $
b0000000000000100 %
1&
b0000000000000100 +
#150000
0&
#155000
b0000000000000100 $
b0000000000000101 %
1&
b0000000000000101 +
1,
#160000
0&
#165000
1#
b0000000000000000 $
b0000000000000001 %
1&
b0000000000000001 +
0,
#170000
0&
1(
#175000
0#
b0000000000000001 $
b0000000000000010 %
1&
b0000000000000010 +
#180000
0&
#185000
b0000000000000010 $
b0000000000000011 %
1&
b0000000000000011 +
#190000
0&
0(
#195000
b0000000000000011 $
b0000000000000100 %
1&
b0000000000000100 +
#200000
0&
#205000
b0000000000000100 $
b0000000000000101 %
1&
b0000000000000101 +
1,
#210000
0&
#215000
1#
b0000000000000000 $
b0000000000000001 %
1&
b0000000000000001 +
0,
#220000
0&
#225000
b0000000000000001 $
b0000000000000010 %
1&
b0000000000000010 +
#230000
0&
#235000
b0000000000000010 $
b0000000000000011 %
1&
b0000000000000011 +
#240000
0&
#245000
b0000000000000011 $
b0000000000000100 %
1&
b0000000000000100 +
#250000
0&
#255000
b0000000000000100 $
b0000000000000101 %
1&
b0000000000000101 +
1,
#260000
0&
#265000
0#
b0000000000000000 $
b0000000000000001 %
1&
b0000000000000001 +
0,
#270000
0&
#275000
b0000000000000001 $
b0000000000000010 %
1&
b0000000000000010 +
#280000
0&
#285000
b0000000000000010 $
b0000000000000011 %
1&
b0000000000000011 +
#290000
0&
#295000
b0000000000000011 $
b0000000000000100 %
1&
b0000000000000100 +
#300000
0&
#305000
b0000000000000100 $
b0000000000000101 %
1&
b0000000000000101 +
1,
#310000
0&
#315000
1#
b0000000000000000 $
b0000000000000001 %
1&
b0000000000000001 +
0,
#320000
0&
#325000
b0000000000000001 $
b0000000000000010 %
1&
b0000000000000010 +
#330000
0&
#335000
b0000000000000010 $
b0000000000000011 %
1&
b0000000000000011 +
#340000
0&
#345000
b0000000000000011 $
b0000000000000100 %
1&
b0000000000000100 +
#350000
0&
#355000
b0000000000000100 $
b0000000000000101 %
1&
b0000000000000101 +
1,
#360000
0&
#365000
0#
b0000000000000000 $
b0000000000000001 %
1&
b0000000000000001 +
0,
#370000
0&
#375000
b0000000000000001 $
b0000000000000010 %
1&
b0000000000000010 +
#380000
0&
#385000
b0000000000000010 $
b0000000000000011 %
1&
b0000000000000011 +
#390000
0&
#395000
b0000000000000011 $
b0000000000000100 %
1&
b0000000000000100 +
#400000
0&
#405000
b0000000000000100 $
b0000000000000101 %
1&
b0000000000000101 +
1,
#410000
0&
#415000
1#
b0000000000000000 $
b0000000000000001 %
1&
b0000000000000001 +
0,
#420000
0&
#425000
b0000000000000001 $
b0000000000000010 %
1&
b0000000000000010 +
#430000
0&
#435000
b0000000000000010 $
b0000000000000011 %
1&
b0000000000000011 +
#440000
0&
#445000
b0000000000000011 $
b0000000000000100 %
1&
b0000000000000100 +
#450000
0&
#455000
b0000000000000100 $
b0000000000000101 %
1&
b0000000000000101 +
1,
#460000
0&
#465000
0#
b0000000000000000 $
b0000000000000001 %
1&
b0000000000000001 +
0,
#470000
0&
#475000
b0000000000000001 $
b0000000000000010 %
1&
b0000000000000010 +
#480000
0&
#485000
b0000000000000010 $
b0000000000000011 %
1&
b0000000000000011 +
#490000
0&
#495000
b0000000000000011 $
b0000000000000100 %
1&
b0000000000000100 +
#500000
0&
#505000
b0000000000000100 $
b0000000000000101 %
1&
b0000000000000101 +
1,
#510000
0&
#515000
1#
b0000000000000000 $
b0000000000000001 %
1&
b0000000000000001 +
0,
#520000
0&
#525000
b0000000000000001 $
b0000000000000010 %
1&
b0000000000000010 +
#530000
0&
#535000
b0000000000000010 $
b0000000000000011 %
1&
b0000000000000011 +
#540000
0&
#545000
b0000000000000011 $
b0000000000000100 %
1&
b0000000000000100 +
#550000
0&
#555000
b0000000000000100 $
b0000000000000101 %
1&
b0000000000000101 +
1,
#560000
0&
#565000
0#
b0000000000000000 $
b0000000000000001 %
1&
b0000000000000001 +
0,
#570000
0&
#575000
b0000000000000001 $
b0000000000000010 %
1&
b0000000000000010 +
#580000
0&
#585000
b0000000000000010 $
b0000000000000011 %
1&
b0000000000000011 +
#590000
0&
#595000
b0000000000000011 $
b0000000000000100 %
1&
b0000000000000100 +
#600000
0&
#605000
b0000000000000100 $
b0000000000000101 %
1&
b0000000000000101 +
1,
#610000
0&
#615000
1#
b0000000000000000 $
b0000000000000001 %
1&
b0000000000000001 +
0,
#620000
0&
#625000
b0000000000000001 $
b0000000000000010 %
1&
b0000000000000010 +
#630000
0&
#635000
b0000000000000010 $
b0000000000000011 %
1&
b0000000000000011 +
#640000
0&
#645000
b0000000000000011 $
b0000000000000100 %
1&
b0000000000000100 +
#650000
0&
#655000
b0000000000000100 $
b0000000000000101 %
1&
b0000000000000101 +
1,
#660000
0&
#665000
0#
b0000000000000000 $
b0000000000000001 %
1&
b0000000000000001 +
0,
#670000
0&
#675000
b0000000000000001 $
b0000000000000010 %
1&
b0000000000000010 +
#680000
0&
#685000
b0000000000000010 $
b0000000000000011 %
1&
b0000000000000011 +
#690000
0&
b0000000000000010 *
1,
#695000
1#
b0000000000000000 $
b0000000000000001 %
1&
b0000000000000001 +
0,
#700000
0&
#705000
b0000000000000001 $
b0000000000000010 %
1&
b0000000000000010 +
#710000
0&
#715000
b0000000000000010 $
b0000000000000011 %
1&
b0000000000000011 +
1,
#720000
0&
#725000
0#
b0000000000000000 $
b0000000000000001 %
1&
b0000000000000001 +
0,
#730000
0&
#735000
b0000000000000001 $
b0000000000000010 %
1&
b0000000000000010 +
#740000
0&
#745000
b0000000000000010 $
b0000000000000011 %
1&
b0000000000000011 +
1,
#750000
0&
#755000
1#
b0000000000000000 $
b0000000000000001 %
1&
b0000000000000001 +
0,
#760000
0&
#765000
b0000000000000001 $
b0000000000000010 %
1&
b0000000000000010 +
#770000
0&
#775000
b0000000000000010 $
b0000000000000011 %
1&
b0000000000000011 +
1,
#780000
0&
#785000
0#
b0000000000000000 $
b0000000000000001 %
1&
b0000000000000001 +
0,
#790000
0&
#795000
b0000000000000001 $
b0000000000000010 %
1&
b0000000000000010 +
#800000
0&
#805000
b0000000000000010 $
b0000000000000011 %
1&
b0000000000000011 +
1,
#810000
0&
#815000
1#
b0000000000000000 $
b0000000000000001 %
1&
b0000000000000001 +
0,
#820000
0&
#825000
b0000000000000001 $
b0000000000000010 %
1&
b0000000000000010 +
#830000
0&
#835000
b0000000000000010 $
b0000000000000011 %
1&
b0000000000000011 +
1,
#840000
0&
#845000
0#
b0000000000000000 $
b0000000000000001 %
1&
b0000000000000001 +
0,
#850000
0&
#855000
b0000000000000001 $
b0000000000000010 %
1&
b0000000000000010 +
#860000
0&
#865000
b0000000000000010 $
b0000000000000011 %
1&
b0000000000000011 +
1,
#870000
0&
#875000
1#
b0000000000000000 $
b0000000000000001 %
1&
b0000000000000001 +
0,
#880000
0&
#885000
b0000000000000001 $
b0000000000000010 %
1&
b0000000000000010 +
#890000
0&
#895000
b0000000000000010 $
b0000000000000011 %
1&
b0000000000000011 +
1,
#900000
0&
#905000
0#
b0000000000000000 $
b0000000000000001 %
1&
b0000000000000001 +
0,
#910000
0&
#915000
b0000000000000001 $
b0000000000000010 %
1&
b0000000000000010 +
#920000
0&
#925000
b0000000000000010 $
b0000000000000011 %
1&
b0000000000000011 +
1,
#930000
0&
#935000
1#
b0000000000000000 $
b0000000000000001 %
1&
b0000000000000001 +
0,
#940000
0&
#945000
b0000000000000001 $
b0000000000000010 %
1&
b0000000000000010 +
#950000
0&
#955000
b0000000000000010 $
b0000000000000011 %
1&
b0000000000000011 +
1,
#960000
0&
#965000
0#
b0000000000000000 $
b0000000000000001 %
1&
b0000000000000001 +
0,
#970000
0&
#975000
b0000000000000001 $
b0000000000000010 %
1&
b0000000000000010 +
#980000
0&
#985000
b0000000000000010 $
b0000000000000011 %
1&
b0000000000000011 +
1,
#990000
0&
#995000
1#
b0000000000000000 $
b0000000000000001 %
1&
b0000000000000001 +
0,
#1000000
0&
#1005000
b0000000000000001 $
b0000000000000010 %
1&
b0000000000000010 +
#1010000
0&
#1015000
b0000000000000010 $
b0000000000000011 %
1&
b0000000000000011 +
1,
#1020000
0&
#1025000
0#
b0000000000000000 $
b0000000000000001 %
1&
b0000000000000001 +
0,
#1030000
0&
#1035000
b0000000000000001 $
b0000000000000010 %
1&
b0000000000000010 +
#1040000
0&
#1045000
b0000000000000010 $
b0000000000000011 %
1&
b0000000000000011 +
1,
#1050000
0&
#1055000
1#
b0000000000000000 $
b0000000000000001 %
1&
b0000000000000001 +
0,
#1060000
0&
#1065000
b0000000000000001 $
b0000000000000010 %
1&
b0000000000000010 +
#1070000
0&
#1075000
b0000000000000010 $
b0000000000000011 %
1&
b0000000000000011 +
1,
#1080000
0&
#1085000
0#
b0000000000000000 $
b0000000000000001 %
1&
b0000000000000001 +
0,
#1090000
0&
#1095000
b0000000000000001 $
b0000000000000010 %
1&
b0000000000000010 +
#1100000
0&
#1105000
b0000000000000010 $
b0000000000000011 %
1&
b0000000000000011 +
1,
#1110000
0&
#1115000
1#
b0000000000000000 $
b0000000000000001 %
1&
b0000000000000001 +
0,
#1120000
0&
#1125000
b0000000000000001 $
b0000000000000010 %
1&
b0000000000000010 +
#1130000
0&
#1135000
b0000000000000010 $
b0000000000000011 %
1&
b0000000000000011 +
1,
#1140000
0&
#1145000
0#
b0000000000000000 $
b0000000000000001 %
1&
b0000000000000001 +
0,
#1150000
0&
#1155000
b0000000000000001 $
b0000000000000010 %
1&
b0000000000000010 +
#1160000
0&
#1165000
b0000000000000010 $
b0000000000000011 %
1&
b0000000000000011 +
1,
#1170000
0&
#1175000
1#
b0000000000000000 $
b0000000000000001 %
1&
b0000000000000001 +
0,
#1180000
0&
#1185000
b0000000000000001 $
b0000000000000010 %
1&
b0000000000000010 +
#1190000
0&
0)
b0000000000000001 +
